Metadata-Version: 1.1
Name: mojapi
Version: 0.1.1
Summary: Python library for interacting with Mojang APIs
Home-page: https://github.com/zugmc/mojapi/
Author: gozug
Author-email: gozug@zugmc.com
License: MIT
Download-URL: https://github.com/zugmc/mojapi/tarball/0.1.1
Keywords: minecraft mojang api
Platform: UNKNOWN
Classifier: Development Status :: 3 - Alpha
Classifier: Intended Audience :: Developers
Classifier: License :: OSI Approved :: MIT License
Classifier: Programming Language :: Python :: 3
Classifier: Programming Language :: Python :: 3.3
Classifier: Programming Language :: Python :: 3.4
Classifier: Programming Language :: Python :: 3.5
